vegomatic/__init__.py
vegomatic/datafetch/__init__.py
vegomatic/datafetch/datafetch.py
vegomatic/datafile/__init__.py
vegomatic/datafile/fileparse.py
vegomatic/datafile/fileset.py
vegomatic/datamap/__init__.py
vegomatic/datamap/mapmaker.py
vegomatic/datamap/objutils.py
vegomatic/gqlf_github/__init__.py
vegomatic/gqlf_github/gqlfetch_github.py
vegomatic/gqlf_linear/__init__.py
vegomatic/gqlf_linear/gqlfetch_linear.py
vegomatic/gqlfetch/__init__.py
vegomatic/gqlfetch/gqlfetch.py
vegomatic/simpledb/__init__.py
vegomatic/simpledb/simpledb.py
vegomatic-0.3.0.dist-info/LICENSE
vegomatic-0.3.0.dist-info/METADATA
vegomatic-0.3.0.dist-info/WHEEL
vegomatic-0.3.0.dist-info/RECORD
