Metadata-Version: 2.3
Name: vegomatic
Version: 0.3.0
Summary: Veg-o-Matic is a multi-module library of various Python Utilities that I have evolved over the years. It originally started as PyDataXlate to provide a data driven field mapping of data sources that I used for various website migrations.
Author: Mark Gooderum
Author-email: 3393412+markfrommn@users.noreply.github.com
Requires-Python: >=3.10,<4
Classifier: Programming Language :: Python :: 3
Classifier: Programming Language :: Python :: 3.10
Classifier: Programming Language :: Python :: 3.11
Classifier: Programming Language :: Python :: 3.12
Classifier: Programming Language :: Python :: 3.13
Requires-Dist: ciso8601 (>=2.3.2,<3.0.0)
Requires-Dist: dumper (>=1.2.0,<2.0.0)
Requires-Dist: gql[all] (>=3.5.0,<4.0.0)
Requires-Dist: mysql-connector-python (>=9.4.0,<10.0.0)
Requires-Dist: pandas (>=2.2.3,<3.0.0)
Requires-Dist: pydal (>=20250629.2,<20250630.0)
